LICENSE
README.md
setup.py
embodied/__init__.py
embodied.egg-info/PKG-INFO
embodied.egg-info/SOURCES.txt
embodied.egg-info/dependency_links.txt
embodied.egg-info/requires.txt
embodied.egg-info/top_level.txt
embodied/core/__init__.py
embodied/core/base.py
embodied/core/driver.py
embodied/core/prefetch.py
embodied/core/random_agent.py
embodied/core/space.py
embodied/core/wrappers.py
embodied/replay/__init__.py
embodied/replay/chunk.py
embodied/replay/indexdict.py
embodied/replay/limiters.py
embodied/replay/replay.py
embodied/replay/sampletree.py
embodied/replay/selectors.py
embodied/run/__init__.py
embodied/run/eval_only.py
embodied/run/parallel.py
embodied/run/parallel_with_eval.py
embodied/run/train.py
embodied/run/train_eval.py
embodied/run/train_holdout.py