Metadata-Version: 2.1
Name: embodied
Version: 1.2.0
Summary: Fast reinforcement learning research
Home-page: http://github.com/danijar/embodied
Author: Danijar Hafner
Author-email: mail@danijar.com
Classifier: Intended Audience :: Science/Research
Classifier: License :: OSI Approved :: MIT License
Classifier: Programming Language :: Python :: 3
Classifier: Topic :: Scientific/Engineering :: Artificial Intelligence
Provides-Extra: dreamerv3
License-File: LICENSE
